{
	"info": {
		"_postman_id": "bf956d82-b4bf-4779-b8b2-29e65d84c2d9",
		"name": "swpark",
		"schema": "https://schema.getpostman.com/json/collection/v2.1.0/collection.json"
	},
	"item": [
		{
			"name": "https://jsonplaceholder.typicode.com/users",
			"event": [
				{
					"listen": "test",
					"script": {
						"id": "107850be-652b-47ec-93c1-3d3828b91007",
						"exec": [
							"pm.test(\"Status code is 200\", function () {",
							"    pm.response.to.have.status(200);",
							"});",
							"",
							"pm.test(\"Your test name\", function () {",
							"    var jsonData = pm.response.json();",
							"    pm.expect(jsonData.length).to.eql(10);",
							"    pm.expect(jsonData[0].username).to.eql(\"Bret1\");",
							"});"
						],
						"type": "text/javascript"
					}
				}
			],
			"request": {
				"method": "GET",
				"header": [],
				"url": {
					"raw": "https://jsonplaceholder.typicode.com/users",
					"protocol": "https",
					"host": [
						"jsonplaceholder",
						"typicode",
						"com"
					],
					"path": [
						"users"
					]
				}
			},
			"response": []
		}
	]
}